Workbook

Sheet PROJECTS
A1: ProjectID | B1: ProjectName | C1: Department | D1: ProjectManager | E1: Priority | F1: Status | G1: StartDate | H1: PlannedEndDate | I1: ActualEndDate | J1: ProjectBudget | K1: IsSOXRelevant
A2: PRJ-001 | B2: ERP System Upgrade | C2: Finance | D2: Anna Kowalski | E2: High | F2: Completed | G2: 45301 | H2: 45473 | I2: 2024-07-45 | J2: 850000 | K2: Yes
A3: PRJ-002 | B3: SOX Remediation Program | C3: Compliance | D3: Marco Rossi | E3: High | F3: Active | G3: 45323 | H3: 45657 | J3: 320000 | K3: Yes
A4: PRJ-003 | B4: Cloud Infrastructure Migration | C4: IT | D4: David Chen | E4: High | F4: Active | G4: 45366 | H4: 45626 | J4: 1200000 | K4: Yes
A5: PRJ-004 | B5: HR System Implementation | C5: HR | D5: Sarah Johnson | E5: Medium | F5: Active | G5: 45383 | H5: 45596 | J5: 450000 | K5: No
A6: PRJ-005 | B6: Data Warehouse Consolidation | C6: IT | D6: Anna Kowalski | E6: High | F6: Active | G6: 45311 | H6: 45565 | J6: 780000 | K6: Yes
A7: PRJ-006 | B7: Internal Audit Tool Deployment | C7: Compliance | D7: Marco Rossi | E7: High | F7: Completed | G7: 45296 | H7: 45412 | I7: 45424 | J7: 230000 | K7: Yes
A8: PRJ-007 | B8: Branch Network Expansion | C8: Operations | D8: Elena Petrova | E8: Medium | F8: Active | G8: 45413 | H8: 45657 | J8: 560000 | K8: No
A9: PRJ-008 | B9: Cybersecurity Framework Update | C9: IT | D9: David Chen | E9: High | F9: Active | G9: 45337 | H9: 45535 | J9: 390000 | K9: Yes
A10: PRJ-009 | B10: Finance Reporting Automation | C10: Finance | D10: Sarah Johnson | E10: High | F10: Delayed | G10: 45352 | H10: 45504 | J10: 670000 | K10: Yes
A11: PRJ-010 | B11: Vendor Management Platform | C11: Procurement | D11: James Okafor | E11: Medium | F11: Active | G11: 45397 | H11: 45626 | J11: 310000 | K11: No
A12: PRJ-011 | B12: Business Continuity Planning | C12: Risk | D12: Elena Petrova | E12: High | F12: Active | G12: 45306 | H12: 45473 | J12: 180000 | K12: Yes
A13: PRJ-012 | B13: Access Control Remediation | C13: IT | D13: David Chen | E13: High | F13: Completed | G13: 45323 | H13: 45443 | I13: 45458 | J13: 140000 | K13: Yes
A14: PRJ-013 | B14: Regulatory Reporting Upgrade | C14: Compliance | D14: Marco Rossi | E14: High | F14: Active | G14: 45413 | H14: 45657 | J14: 520000 | K14: Yes
A15: PRJ-014 | B15: Budget Planning Tool Rollout | C15: Finance | D15: Anna Kowalski | E15: Medium | F15: On Hold | G15: 45352 | H15: 45565 | J15: 290000 | K15: Yes
A16: PRJ-015 | B16: Supply Chain Digitization | C16: Operations | D16: James Okafor | E16: Medium | F16: Active | G16: 45383 | H16: 45596 | J16: 410000 | K16: No
A17: PRJ-016 | B17: Identity Management Overhaul | C17: IT | D17: David Chen | E17: High | F17: Active | G17: 45444 | H17: 45688 | J17: 680000 | K17: Yes
A18: PRJ-017 | B18: SOX Training Program | C18: Compliance | D18: Elena Petrova | E18: Medium | F18: Completed | G18: 45301 | H18: 45382 | I18: 45379 | J18: 85000 | K18: Yes
A19: PRJ-018 | B19: Financial Close Optimization | C19: Finance | D19: Anna Kowalski | E19: High | F19: Active | G19: 45427 | H19: 45626 | J19: 430000 | K19: Yes
A20: PRJ-019 | B20: Procurement Compliance Review | C20: Procurement | D20: James Okafor | E20: Medium | F20: Active | G20: 45444 | H20: 45657 | J20: 195000 | K20: Yes
A21: PRJ-020 | B21: IT Disaster Recovery Update | C21: IT | D21: David Chen | E21: High | F21: Delayed | G21: 45323 | H21: 45504 | J21: 360000 | K21: Yes
A22: PRJ-021 | B22: Internal Controls Documentation | C22: Compliance | D22: Marco Rossi | E22: High | F22: Active | G22: 45352 | H22: 45565 | J22: 215000 | K22: Yes
A23: PRJ-022 | B23: Payroll System Migration | C23: HR | D23: Sarah Johnson | E23: Medium | F23: Active | G23: 45413 | H23: 45626 | J23: 375000 | K23: Yes
A24: PRJ-023 | B24: Customer Data Governance | C24: IT | D24: Elena Petrova | E24: High | F24: Active | G24: 45397 | H24: 45596 | J24: 490000 | K24: No
A25: PRJ-024 | B25: Fixed Assets Management Update | C25: Finance | D25: Anna Kowalski | E25: Medium | F25: Completed | G25: 45306 | H25: 45443 | I25: 45432 | J25: 165000 | K25: Yes
A26: PRJ-025 | B26: Change Management Framework | C26: PMO | D26: Marco Rossi | E26: Medium | F26: Active | G26: 45444 | H26: 45657 | J26: 145000 | K26: No
A27: PRJ-026 | B27: Audit Evidence Repository | C27: Compliance | D27: Elena Petrova | E27: High | F27: Active | G27: 45366 | H27: 45565 | J27: 275000 | K27: Yes
A28: PRJ-027 | B28: Tax Reporting Compliance | C28: Finance | D28: Sarah Johnson | E28: High | F28: Active | G28: 45413 | H28: 45657 | J28: 340000 | K28: Yes
A29: PRJ-028 | B29: Network Security Hardening | C29: IT | D29: David Chen | E29: High | F29: Completed | G29: 45311 | H29: 45412 | I29: 45407 | J29: 220000 | K29: Yes
A30: PRJ-029 | B30: Operational Risk Framework | C30: Risk | D30: James Okafor | E30: High | F30: Active | G30: 45383 | H30: 45596 | J30: 285000 | K30: Yes
A31: PRJ-030 | B31: PMO Dashboard Implementation | C31: PMO | D31: Anna Kowalski | E31: High | F31: Active | G31: 45444 | H31: 45657 | J31: 195000 | K31: No

Sheet CONTROLS
A1: ControlID | B1: ControlName | C1: ControlDescription | D1: ControlType | E1: RiskRating | F1: ControlOwner | G1: Department | H1: TestingFrequency | I1: ITGCCategory | J1: Status | K1: LastTestedDate | L1: EvidenceStatus
A2: CTR-001 | B2: Quarterly User Access Review | C2: All user accounts in financial systems are reviewed quarterly to ensure access matches current job roles | D2: Detective | E2: High | F2: David Chen | G2: IT | H2: Quarterly | I2: Access Management | J2: Active | K2: 45473 | L2: Collected
A3: CTR-002 | B3: Privileged Access Monitoring | C3: Privileged and admin accounts are logged and reviewed monthly for unauthorized activity | D3: Detective | E3: Critical | F3: David Chen | G3: IT | H3: Quarterly | I3: Access Management | J3: Active | K3: 45473 | L3: Collected
A4: CTR-003 | B4: Segregation of Duties Enforcement | C4: No single user has both transaction initiation and approval rights in financial systems | D4: Preventive | E4: Critical | F4: Anna Kowalski | G4: Finance | H4: Quarterly | I4: Access Management | J4: Active | K4: 45473 | L4: Pending
A5: CTR-004 | B5: New User Access Provisioning | C5: New employees receive system access only after formal approval from their line manager and IT Security | D5: Preventive | E5: High | F5: David Chen | G5: IT | H5: Quarterly | I5: Access Management | J5: Active | K5: 45473 | L5: Collected
A6: CTR-005 | B6: Terminated User Access Revocation | C6: Access for all terminated employees is revoked within 24 hours of HR notification | D6: Preventive | E6: Critical | F6: David Chen | G6: IT | H6: Quarterly | I6: Access Management | J6: Active | K6: 45473 | L6: Missing
A7: CTR-006 | B7: Change Management Approval | C7: All changes to financial systems require formal approval through the change advisory board | D7: Preventive | E7: High | F7: Marco Rossi | G7: Compliance | H7: Quarterly | I7: Change Management | J7: Active | K7: 45382 | L7: Collected
A8: CTR-007 | B8: Emergency Change Procedure | C8: Emergency changes to production systems follow a documented expedited process with post-implementation review | D8: Preventive | E8: High | F8: David Chen | G8: IT | H8: Semi-Annual | I8: Change Management | J8: Active | K8: 45473 | L8: Collected
A9: CTR-008 | B9: Change Testing and Validation | C9: All system changes are tested in a non-production environment before deployment to production | D9: Preventive | E9: High | F9: David Chen | G9: IT | H9: Quarterly | I9: Change Management | J9: Active | K9: 45473 | L9: Pending
A10: CTR-009 | B10: Release Management Control | C10: Software releases follow a documented release management process with version control | D10: Preventive | E10: Medium | F10: David Chen | G10: IT | H10: Semi-Annual | I10: Change Management | J10: Active | K10: 45473 | L10: Collected
A11: CTR-010 | B11: Patch Management Process | C11: Security patches are applied within 30 days of release for critical systems | D11: Preventive | E11: High | F11: David Chen | G11: IT | H11: Quarterly | I11: Operations | J11: Active | K11: 45473 | L11: Collected
A12: CTR-011 | B12: Backup and Recovery Testing | C12: System backups are performed daily and recovery is tested quarterly | D12: Detective | E12: High | F12: David Chen | G12: IT | H12: Quarterly | I12: Operations | J12: Active | K12: 45473 | L12: Collected
A13: CTR-012 | B13: System Availability Monitoring | C13: Critical financial systems are monitored 24/7 with automated alerting for downtime | D13: Detective | E13: Medium | F13: David Chen | G13: IT | H13: Quarterly | I13: Operations | J13: Active | K13: 45473 | L13: Collected
... A51: CTR-050 | B51: Management Override Monitoring | C51: Any management override of system controls is logged reviewed and approved by the Audit Committee | D51: Detective | E51: Critical | F51: Marco Rossi | G51: Compliance | H51: Quarterly | I51: Financial Reporting | J51: Active | K51: 45473 | L51: Pending

Sheet AUDIT FINDINGS
A1: FindingID | B1: ControlID | C1: ProjectID | D1: FindingTitle | E1: Severity | F1: RootCause | G1: FindingOwner | H1: DateIdentified | I1: DaysOpen | J1: RemediationDeadline | K1: RemediationStatus | L1: DateClosed | M1: AuditCycle
A2: FND-001 | B2: CTR-005 | C2: PRJ-012 | D2: Terminated employee accounts not revoked within SLA | E2: Critical | F2: HR offboarding process does not notify IT Security automatically | G2: David Chen | H2: 45306 | I2: =IF(AUDIT_FINDINGS[[#This Row],[RemediationStatus]]="Closed",AUDIT_FINDINGS[[#This Row],[DateClosed]]-AUDIT_FINDINGS[[#This Row],[DateIdentified]],TODAY()-AUDIT_FINDINGS[[#This Row],[DateIdentified]]) -> 26 | J2: 45337 | K2: Closed | L2: 45332 | M2: 2024-Q1
A3: FND-002 | B3: CTR-003 | C3: PRJ-001 | D3: SOD conflict detected for 3 Finance users | E3: Critical | F3: Role assignment process does not check for SoD conflicts | G3: Anna Kowalski | H3: 45311 | I3: =IF(AUDIT_FINDINGS[[#This Row],[RemediationStatus]]="Closed",AUDIT_FINDINGS[[#This Row],[DateClosed]]-AUDIT_FINDINGS[[#This Row],[DateIdentified]],TODAY()-AUDIT_FINDINGS[[#This Row],[DateIdentified]]) -> 29 | J3: 45342 | K3: Closed | L3: 45340 | M3: 2024-Q1
A4: FND-003 | B4: CTR-017 | C4: PRJ-005 | D4: Account reconciliation completed 12 days after deadline | E4: High | F4: Understaffed finance team during peak period | G4: Anna Kowalski | H4: 45316 | I4: =IF(AUDIT_FINDINGS[[#This Row],[RemediationStatus]]="Closed",AUDIT_FINDINGS[[#This Row],[DateClosed]]-AUDIT_FINDINGS[[#This Row],[DateIdentified]],TODAY()-AUDIT_FINDINGS[[#This Row],[DateIdentified]]) -> 28 | J4: 45347 | K4: Closed | L4: 45344 | M4: 2024-Q1
A5: FND-004 | B5: CTR-008 | C5: PRJ-003 | D5: Change deployed to production without test evidence | E5: High | F5: Test environment was unavailable due to infrastructure issue | G5: David Chen | H5: 45327 | I5: =IF(AUDIT_FINDINGS[[#This Row],[RemediationStatus]]="Closed",AUDIT_FINDINGS[[#This Row],[DateClosed]]-AUDIT_FINDINGS[[#This Row],[DateIdentified]],TODAY()-AUDIT_FINDINGS[[#This Row],[DateIdentified]]) -> 25 | J5: 45356 | K5: Closed | L5: 45352 | M5: 2024-Q1
A6: FND-005 | B6: CTR-020 | C6: PRJ-001 | D6: Intercompany reconciliation not completed for January close | E6: High | F6: Manual process with no automated reminder or escalation | G6: Anna Kowalski | H6: 45332 | I6: =IF(AUDIT_FINDINGS[[#This Row],[RemediationStatus]]="Closed",AUDIT_FINDINGS[[#This Row],[DateClosed]]-AUDIT_FINDINGS[[#This Row],[DateIdentified]],TODAY()-AUDIT_FINDINGS[[#This Row],[DateIdentified]]) -> 27 | J6: 45361 | K6: Closed | L6: 45359 | M6: 2024-Q1
A7: FND-006 | B7: CTR-024 | C7: PRJ-010 | D7: 14 vendor accounts active beyond contract end date | E7: High | F7: No automated deprovisioning for vendor access | G7: David Chen | H7: 45337 | I7: =IF(AUDIT_FINDINGS[[#This Row],[RemediationStatus]]="Closed",AUDIT_FINDINGS[[#This Row],[DateClosed]]-AUDIT_FINDINGS[[#This Row],[DateIdentified]],TODAY()-AUDIT_FINDINGS[[#This Row],[DateIdentified]]) -> 26 | J7: 45366 | K7: Closed | L7: 45363 | M7: 2024-Q1
A8: FND-007 | B8: CTR-015 | C8: PRJ-001 | D8: 5 journal entries posted without secondary approval | E8: Critical | F8: System workflow bypassed due to month-end time pressure | G8: Anna Kowalski | H8: 45342 | I8: =IF(AUDIT_FINDINGS[[#This Row],[RemediationStatus]]="Closed",AUDIT_FINDINGS[[#This Row],[DateClosed]]-AUDIT_FINDINGS[[#This Row],[DateIdentified]],TODAY()-AUDIT_FINDINGS[[#This Row],[DateIdentified]]) -> 24 | J8: 45371 | K8: Closed | L8: 45366 | M8: 2024-Q1
A9: FND-008 | B9: CTR-010 | C9: PRJ-008 | D9: Critical security patches not applied within 30-day SLA | E9: High | F9: Patch management tool misconfigured for new server group | G9: David Chen | H9: 45352 | I9: =IF(AUDIT_FINDINGS[[#This Row],[RemediationStatus]]="Closed",AUDIT_FINDINGS[[#This Row],[DateClosed]]-AUDIT_FINDINGS[[#This Row],[DateIdentified]],TODAY()-AUDIT_FINDINGS[[#This Row],[DateIdentified]]) -> 27 | J9: 45383 | K9: Closed | L9: 45379 | M9: 2024-Q1
A10: FND-009 | B10: CTR-033 | C10: PRJ-008 | D10: Firewall review not completed for Q1 | E10: High | F10: Responsible engineer on extended leave with no backup assigned | G10: David Chen | H10: 45361 | I10: =IF(AUDIT_FINDINGS[[#This Row],[RemediationStatus]]="Closed",AUDIT_FINDINGS[[#This Row],[DateClosed]]-AUDIT_FINDINGS[[#This Row],[DateIdentified]],TODAY()-AUDIT_FINDINGS[[#This Row],[DateIdentified]]) -> 26 | J10: 45392 | K10: Closed | L10: 45387 | M10: 2024-Q1
A11: FND-010 | B11: CTR-039 | C11: PRJ-013 | D11: Regulatory report submitted without CFO review | E11: Critical | F11: Approval workflow not enforced in reporting tool | G11: Marco Rossi | H11: 45366 | I11: =IF(AUDIT_FINDINGS[[#This Row],[RemediationStatus]]="Closed",AUDIT_FINDINGS[[#This Row],[DateClosed]]-AUDIT_FINDINGS[[#This Row],[DateIdentified]],TODAY()-AUDIT_FINDINGS[[#This Row],[DateIdentified]]) -> 26 | J11: 45397 | K11: Closed | L11: 45392 | M11: 2024-Q1
A12: FND-011 | B12: CTR-001 | C12: PRJ-016 | D12: Q1 access review completed 18 days late | E12: High | F12: No automated reminder system for review deadlines | G12: David Chen | H12: 45387 | I12: =IF(AUDIT_FINDINGS[[#This Row],[RemediationStatus]]="Closed",AUDIT_FINDINGS[[#This Row],[DateClosed]]-AUDIT_FINDINGS[[#This Row],[DateIdentified]],TODAY()-AUDIT_FINDINGS[[#This Row],[DateIdentified]]) -> 25 | J12: 45417 | K12: Closed | L12: 45412 | M12: 2024-Q2
A13: FND-012 | B13: CTR-027 | C13: PRJ-019 | D13: 23 invoices paid without three-way match completion | E13: Critical | F13: Three-way match bypassed for urgent vendor payments | G13: James Okafor | H13: 45392 | I13: =IF(AUDIT_FINDINGS[[#This Row],[RemediationStatus]]="Closed",AUDIT_FINDINGS[[#This Row],[DateClosed]]-AUDIT_FINDINGS[[#This Row],[DateIdentified]],TODAY()-AUDIT_FINDINGS[[#This Row],[DateIdentified]]) -> 26 | J13: 45422 | K13: Closed | L13: 45418 | M13: 2024-Q2
A14: FND-013 | B14: CTR-016 | C14: PRJ-018 | D14: Financial close checklist missing CFO signature for March | E14: High | F14: Checklist submitted digitally but signature field was optional | G14: Anna Kowalski | H14: 45397 | I14: =IF(AUDIT_FINDINGS[[#This Row],[RemediationStatus]]="Closed",AUDIT_FINDINGS[[#This Row],[DateClosed]]-AUDIT_FINDINGS[[#This Row],[DateIdentified]],TODAY()-AUDIT_FINDINGS[[#This Row],[DateIdentified]]) -> 27 | J14: 45427 | K14: Closed | L14: 45424 | M14: 2024-Q2
A15: FND-014 | B15: CTR-021 | C15: PRJ-016 | D15: SoD monitoring tool offline for 11 days without detection | E15: Critical | F15: Monitoring tool failure not captured by system alerting | G15: David Chen | H15: 45402 | I15: =IF(AUDIT_FINDINGS[[#This Row],[RemediationStatus]]="Closed",AUDIT_FINDINGS[[#This Row],[DateClosed]]-AUDIT_FINDINGS[[#This Row],[DateIdentified]],TODAY()-AUDIT_FINDINGS[[#This Row],[DateIdentified]]) -> 749 | J15: 45432 | K15: In Progress | M15: 2024-Q2
A16: FND-015 | B16: CTR-049 | C16: PRJ-005 | D16: Anti-fraud monitoring alerts not reviewed for 6 weeks | E16: Critical | F16: Alert review process not formally assigned to an owner | G16: Anna Kowalski | H16: 45407 | I16: =IF(AUDIT_FINDINGS[[#This Row],[RemediationStatus]]="Closed",AUDIT_FINDINGS[[#This Row],[DateClosed]]-AUDIT_FINDINGS[[#This Row],[DateIdentified]],TODAY()-AUDIT_FINDINGS[[#This Row],[DateIdentified]]) -> 744 | J16: 45437 | K16: In Progress | M16: 2024-Q2
A17: FND-016 | B17: CTR-037 | C17: PRJ-022 | D17: Payroll changes processed without HR Director approval for 2 employees | E17: Critical | F17: Approval workflow had a configuration error after system update | G17: Sarah Johnson | H17: 45413 | I17: =IF(AUDIT_FINDINGS[[#This Row],[RemediationStatus]]="Closed",AUDIT_FINDINGS[[#This Row],[DateClosed]]-AUDIT_FINDINGS[[#This Row],[DateIdentified]],TODAY()-AUDIT_FINDINGS[[#This Row],[DateIdentified]]) -> 738 | J17: 45444 | K17: In Progress | M17: 2024-Q2
A18: FND-017 | B18: CTR-013 | C18: PRJ-003 | D18: 8 IT incidents not resolved within SLA for April | E18: Medium | F18: Insufficient helpdesk capacity during cloud migration peak | G18: Marco Rossi | H18: 45417 | I18: =IF(AUDIT_FINDINGS[[#This Row],[RemediationStatus]]="Closed",AUDIT_FINDINGS[[#This Row],[DateClosed]]-AUDIT_FINDINGS[[#This Row],[DateIdentified]],TODAY()-AUDIT_FINDINGS[[#This Row],[DateIdentified]]) -> 734 | J18: 45448 | K18: In Progress | M18: 2024-Q2
A19: FND-018 | B19: CTR-004 | C19: PRJ-016 | D19: 3 new users provisioned without documented manager approval | E19: High | F19: Approval form not required in expedited onboarding process | G19: David Chen | H19: 45422 | I19: =IF(AUDIT_FINDINGS[[#This Row],[RemediationStatus]]="Closed",AUDIT_FINDINGS[[#This Row],[DateClosed]]-AUDIT_FINDINGS[[#This Row],[DateIdentified]],TODAY()-AUDIT_FINDINGS[[#This Row],[DateIdentified]]) -> 729 | J19: 45453 | K19: In Progress | M19: 2024-Q2
A20: FND-019 | B20: CTR-019 | C20: PRJ-009 | D20: April financial statements distributed before CFO review | E20: Critical | F20: Distribution list triggered automatically before approval step | G20: Sarah Johnson | H20: 45427 | I20: =IF(AUDIT_FINDINGS[[#This Row],[RemediationStatus]]="Closed",AUDIT_FINDINGS[[#This Row],[DateClosed]]-AUDIT_FINDINGS[[#This Row],[DateIdentified]],TODAY()-AUDIT_FINDINGS[[#This Row],[DateIdentified]]) -> 724 | J20: 45458 | K20: Open | M20: 2024-Q2
A21: FND-020 | B21: CTR-050 | C21: PRJ-002 | D21: Management override of payment limit not reported to Audit Committee | E21: Critical | F21: Override reporting process not documented in procedure | G21: Marco Rossi | H21: 45432 | I21: =IF(AUDIT_FINDINGS[[#This Row],[RemediationStatus]]="Closed",AUDIT_FINDINGS[[#This Row],[DateClosed]]-AUDIT_FINDINGS[[#This Row],[DateIdentified]],TODAY()-AUDIT_FINDINGS[[#This Row],[DateIdentified]]) -> 719 | J21: 45463 | K21: Open | M21: 2024-Q2
A22: FND-021 | B22: CTR-002 | C22: PRJ-016 | D22: Privileged account used for routine tasks over 30-day period | E22: High | F22: IT engineer used admin account for daily operations due to workload | G22: David Chen | H22: 45434 | I22: =IF(AUDIT_FINDINGS[[#This Row],[RemediationStatus]]="Closed",AUDIT_FINDINGS[[#This Row],[DateClosed]]-AUDIT_FINDINGS[[#This Row],[DateIdentified]],TODAY()-AUDIT_FINDINGS[[#This Row],[DateIdentified]]) -> 717 | J22: 45465 | K22: Open | M22: 2024-Q2
A23: FND-022 | B23: CTR-028 | C23: PRJ-018 | D23: Payment of EUR 85000 processed without CFO approval | E23: Critical | F23: Payment system threshold setting was incorrect after upgrade | G23: Sarah Johnson | H23: 45437 | I23: =IF(AUDIT_FINDINGS[[#This Row],[RemediationStatus]]="Closed",AUDIT_FINDINGS[[#This Row],[DateClosed]]-AUDIT_FINDINGS[[#This Row],[DateIdentified]],TODAY()-AUDIT_FINDINGS[[#This Row],[DateIdentified]]) -> 714 | J23: 45468 | K23: Open | M23: 2024-Q2
A24: FND-023 | B24: CTR-003 | C24: PRJ-016 | D24: New SoD conflict introduced during identity management project | E24: High | F24: Project team not consulted compliance team before role changes | G24: Anna Kowalski | H24: 45444 | I24: =IF(AUDIT_FINDINGS[[#This Row],[RemediationStatus]]="Closed",AUDIT_FINDINGS[[#This Row],[DateClosed]]-AUDIT_FINDINGS[[#This Row],[DateIdentified]],TODAY()-AUDIT_FINDINGS[[#This Row],[DateIdentified]]) -> 707 | J24: 45474 | K24: Open | M24: 2024-Q2
A25: FND-024 | B25: CTR-011 | C25: PRJ-020 | D25: Backup recovery test failed for financial reporting database | E25: Critical | F25: Recovery procedure not updated after database migration | G25: David Chen | H25: 45448 | I25: =IF(AUDIT_FINDINGS[[#This Row],[RemediationStatus]]="Closed",AUDIT_FINDINGS[[#This Row],[DateClosed]]-AUDIT_FINDINGS[[#This Row],[DateIdentified]],TODAY()-AUDIT_FINDINGS[[#This Row],[DateIdentified]]) -> 703 | J25: 45478 | K25: Open | M25: 2024-Q2
A26: FND-025 | B26: CTR-005 | C26: PRJ-016 | D26: 4 terminated contractors still have active system access | E26: Critical | F26: Contractor offboarding tracked separately from employee offboarding | G26: David Chen | H26: 45451 | I26: =IF(AUDIT_FINDINGS[[#This Row],[RemediationStatus]]="Closed",AUDIT_FINDINGS[[#This Row],[DateClosed]]-AUDIT_FINDINGS[[#This Row],[DateIdentified]],TODAY()-AUDIT_FINDINGS[[#This Row],[DateIdentified]]) -> 700 | J26: 45481 | K26: Open | M26: 2024-Q2
... A41: FND-040 | B41: CTR-050 | C41: PRJ-021 | D41: Management override log incomplete for Q2 period | E41: High | F41: Override logging process bypassed during system downtime | G41: Marco Rossi | H41: 45471 | I41: =IF(AUDIT_FINDINGS[[#This Row],[RemediationStatus]]="Closed",AUDIT_FINDINGS[[#This Row],[DateClosed]]-AUDIT_FINDINGS[[#This Row],[DateIdentified]],TODAY()-AUDIT_FINDINGS[[#This Row],[DateIdentified]]) -> 680 | J41: 45501 | K41: Open | M41: 2024-Q2

Sheet MILESTONES
A1: MilestoneID | B1: ProjectID | C1: MilestoneName | D1: Phase | E1: PlannedDate | F1: ActualDate | G1: Status | H1: DelayDays | I1: MilestoneOwner | J1: IsCriticalPath
A2: MST-001 | B2: PRJ-001 | C2: Project Charter Approved | D2: Planning | E2: 45311 | F2: 45311 | G2: Completed | H2: 0 | I2: Anna Kowalski | J2: Yes
A3: MST-002 | B3: PRJ-001 | C3: Requirements Gathering Complete | D3: Planning | E3: 45337 | F3: 45340 | G3: Completed | H3: 3 | I3: Anna Kowalski | J3: Yes
A4: MST-003 | B4: PRJ-001 | C4: Vendor Selection Finalized | D4: Planning | E4: 45352 | F4: 45361 | G4: Completed | H4: 9 | I4: Anna Kowalski | J4: No
A5: MST-004 | B5: PRJ-001 | C5: System Configuration Complete | D5: Execution | E5: 45413 | F5: 45432 | G5: Completed | H5: 19 | I5: Anna Kowalski | J5: Yes
A6: MST-005 | B6: PRJ-001 | C6: User Acceptance Testing Complete | D6: Testing | E6: 45458 | F6: 45475 | G6: Completed | H6: 17 | I6: Anna Kowalski | J6: Yes
A7: MST-006 | B7: PRJ-002 | C7: SOX Gap Assessment Complete | D7: Planning | E7: 45350 | F7: 45356 | G7: Completed | H7: 5 | I7: Marco Rossi | J7: Yes
A8: MST-007 | B8: PRJ-002 | C8: Remediation Roadmap Approved | D8: Planning | E8: 45382 | F8: 45392 | G8: Completed | H8: 10 | I8: Marco Rossi | J8: Yes
A9: MST-008 | B9: PRJ-002 | C9: Q1 Remediation Actions Complete | D9: Execution | E9: 45412 | F9: 45427 | G9: Completed | H9: 15 | I9: Marco Rossi | J9: Yes
A10: MST-009 | B10: PRJ-002 | C10: Q2 Remediation Actions Complete | D10: Execution | E10: 45504 | G10: In Progress | I10: Marco Rossi | J10: Yes
A11: MST-010 | B11: PRJ-003 | C11: Cloud Architecture Design Approved | D11: Planning | E11: 45383 | F11: 45387 | G11: Completed | H11: 4 | I11: David Chen | J11: Yes
A12: MST-011 | B12: PRJ-003 | C12: Development Environment Migrated | D12: Execution | E12: 45443 | F12: 45453 | G12: Completed | H12: 10 | I12: David Chen | J12: Yes
A13: MST-012 | B13: PRJ-003 | C13: Production Migration Phase 1 | D13: Execution | E13: 45504 | G13: In Progress | I13: David Chen | J13: Yes
A14: MST-013 | B14: PRJ-003 | C14: Production Migration Phase 2 | D14: Execution | E14: 45565 | G14: Not Started | I14: David Chen | J14: Yes
A15: MST-014 | B15: PRJ-005 | C15: Data Inventory Complete | D15: Planning | E15: 45351 | F15: 45359 | G15: Completed | H15: 8 | I15: Anna Kowalski | J15: Yes
A16: MST-015 | B16: PRJ-005 | C16: ETL Pipeline Development Complete | D16: Execution | E16: 45443 | F16: 45463 | G16: Completed | H16: 20 | I16: Anna Kowalski | J16: Yes
A17: MST-016 | B17: PRJ-005 | C17: Data Validation and Testing Complete | D17: Testing | E17: 45535 | G17: In Progress | I17: Anna Kowalski | J17: Yes
A18: MST-017 | B18: PRJ-008 | C18: Security Framework Assessment | D18: Planning | E18: 45366 | F18: 45366 | G18: Completed | H18: 0 | I18: David Chen | J18: Yes
A19: MST-018 | B19: PRJ-008 | C19: Critical Vulnerability Remediation | D19: Execution | E19: 45443 | F19: 45448 | G19: Completed | H19: 5 | I19: David Chen | J19: Yes
A20: MST-019 | B20: PRJ-008 | C20: Framework Documentation Complete | D20: Execution | E20: 45504 | G20: In Progress | I20: David Chen | J20: No
A21: MST-020 | B21: PRJ-009 | C21: Automation Requirements Defined | D21: Planning | E21: 45383 | F21: 45397 | G21: Completed | H21: 14 | I21: Sarah Johnson | J21: Yes
A22: MST-021 | B22: PRJ-009 | C22: Automation Tool Selected | D22: Planning | E22: 45412 | F22: 45432 | G22: Completed | H22: 20 | I22: Sarah Johnson | J22: Yes
A23: MST-022 | B23: PRJ-009 | C23: Phase 1 Automation Live | D23: Execution | E23: 45473 | G23: Delayed | I23: Sarah Johnson | J23: Yes
A24: MST-023 | B24: PRJ-009 | C24: Phase 2 Automation Live | D24: Execution | E24: 45504 | G24: Not Started | I24: Sarah Johnson | J24: Yes
A25: MST-024 | B25: PRJ-016 | C25: Identity Platform Selected | D25: Planning | E25: 45474 | G25: In Progress | I25: David Chen | J25: Yes
A26: MST-025 | B26: PRJ-016 | C26: Legacy System Decommission Plan | D26: Planning | E26: 45535 | G26: Not Started | I26: David Chen | J26: No
A27: MST-026 | B27: PRJ-020 | C27: DR Assessment Complete | D27: Planning | E27: 45382 | F27: 45402 | G27: Completed | H27: 20 | I27: David Chen | J27: Yes
A28: MST-027 | B28: PRJ-020 | C28: DR Plan Updated | D28: Execution | E28: 45443 | G28: Delayed | I28: David Chen | J28: Yes
A29: MST-028 | B29: PRJ-020 | C29: DR Test Scheduled | D29: Execution | E29: 45504 | G29: Not Started | I29: David Chen | J29: Yes
A30: MST-029 | B30: PRJ-022 | C30: Payroll Data Migration Plan | D30: Planning | E30: 45444 | F30: 45448 | G30: Completed | H30: 4 | I30: Sarah Johnson | J30: Yes
A31: MST-030 | B31: PRJ-022 | C31: Parallel Run Testing | D31: Testing | E31: 45565 | G31: Not Started | I31: Sarah Johnson | J31: Yes

Sheet BUDGET TRACKING
A1: BudgetID | B1: ProjectID | C1: Project name | D1: Month | E1: PlannedSpend | F1: ActualSpend | G1: Variance | H1: VariancePercent | I1: Category | J1: ApprovedBy
A2: BGT-001 | B2: PRJ-001 | C2: =_xlfn.XLOOKUP(BUDGET_TRACKING[[#This Row],[ProjectID]],PROJECTS!A:A,PROJECTS!B:B,"Not Found") -> ERP System Upgrade | D2: 45292 | E2: 85000 | F2: 82000 | G2: =BUDGET_TRACKING[[#This Row],[ActualSpend]]-BUDGET_TRACKING[[#This Row],[PlannedSpend]] -> -3000 | H2: =(BUDGET_TRACKING[[#This Row],[Variance]]/BUDGET_TRACKING[[#This Row],[PlannedSpend]])*100 -> -3.5294118 | I2: Labour | J2: Anna Kowalski
A3: BGT-002 | B3: PRJ-001 | C3: =_xlfn.XLOOKUP(BUDGET_TRACKING[[#This Row],[ProjectID]],PROJECTS!A:A,PROJECTS!B:B,"Not Found") -> ERP System Upgrade | D3: 45323 | E3: 95000 | F3: 98500 | G3: =BUDGET_TRACKING[[#This Row],[ActualSpend]]-BUDGET_TRACKING[[#This Row],[PlannedSpend]] -> 3500 | H3: =(BUDGET_TRACKING[[#This Row],[Variance]]/BUDGET_TRACKING[[#This Row],[PlannedSpend]])*100 -> 3.6842105 | I3: Labour | J3: Anna Kowalski
A4: BGT-003 | B4: PRJ-001 | C4: =_xlfn.XLOOKUP(BUDGET_TRACKING[[#This Row],[ProjectID]],PROJECTS!A:A,PROJECTS!B:B,"Not Found") -> ERP System Upgrade | D4: 45352 | E4: 120000 | F4: 135000 | G4: =BUDGET_TRACKING[[#This Row],[ActualSpend]]-BUDGET_TRACKING[[#This Row],[PlannedSpend]] -> 15000 | H4: =(BUDGET_TRACKING[[#This Row],[Variance]]/BUDGET_TRACKING[[#This Row],[PlannedSpend]])*100 -> 12.5 | I4: Technology | J4: Anna Kowalski
A5: BGT-004 | B5: PRJ-001 | C5: =_xlfn.XLOOKUP(BUDGET_TRACKING[[#This Row],[ProjectID]],PROJECTS!A:A,PROJECTS!B:B,"Not Found") -> ERP System Upgrade | D5: 45383 | E5: 180000 | F5: 195000 | G5: =BUDGET_TRACKING[[#This Row],[ActualSpend]]-BUDGET_TRACKING[[#This Row],[PlannedSpend]] -> 15000 | H5: =(BUDGET_TRACKING[[#This Row],[Variance]]/BUDGET_TRACKING[[#This Row],[PlannedSpend]])*100 -> 8.3333333 | I5: Technology | J5: Anna Kowalski
A6: BGT-005 | B6: PRJ-001 | C6: =_xlfn.XLOOKUP(BUDGET_TRACKING[[#This Row],[ProjectID]],PROJECTS!A:A,PROJECTS!B:B,"Not Found") -> ERP System Upgrade | D6: 45413 | E6: 200000 | F6: 218000 | G6: =BUDGET_TRACKING[[#This Row],[ActualSpend]]-BUDGET_TRACKING[[#This Row],[PlannedSpend]] -> 18000 | H6: =(BUDGET_TRACKING[[#This Row],[Variance]]/BUDGET_TRACKING[[#This Row],[PlannedSpend]])*100 -> 9 | I6: External | J6: Anna Kowalski
A7: BGT-006 | B7: PRJ-001 | C7: =_xlfn.XLOOKUP(BUDGET_TRACKING[[#This Row],[ProjectID]],PROJECTS!A:A,PROJECTS!B:B,"Not Found") -> ERP System Upgrade | D7: 45444 | E7: 170000 | F7: 168500 | G7: =BUDGET_TRACKING[[#This Row],[ActualSpend]]-BUDGET_TRACKING[[#This Row],[PlannedSpend]] -> -1500 | H7: =(BUDGET_TRACKING[[#This Row],[Variance]]/BUDGET_TRACKING[[#This Row],[PlannedSpend]])*100 -> -0.88235294 | I7: Labour | J7: Anna Kowalski
A8: BGT-007 | B8: PRJ-002 | C8: =_xlfn.XLOOKUP(BUDGET_TRACKING[[#This Row],[ProjectID]],PROJECTS!A:A,PROJECTS!B:B,"Not Found") -> SOX Remediation Program | D8: 45323 | E8: 25000 | F8: 24500 | G8: =BUDGET_TRACKING[[#This Row],[ActualSpend]]-BUDGET_TRACKING[[#This Row],[PlannedSpend]] -> -500 | H8: =(BUDGET_TRACKING[[#This Row],[Variance]]/BUDGET_TRACKING[[#This Row],[PlannedSpend]])*100 -> -2 | I8: Labour | J8: Marco Rossi
A9: BGT-008 | B9: PRJ-002 | C9: =_xlfn.XLOOKUP(BUDGET_TRACKING[[#This Row],[ProjectID]],PROJECTS!A:A,PROJECTS!B:B,"Not Found") -> SOX Remediation Program | D9: 45352 | E9: 28000 | F9: 27000 | G9: =BUDGET_TRACKING[[#This Row],[ActualSpend]]-BUDGET_TRACKING[[#This Row],[PlannedSpend]] -> -1000 | H9: =(BUDGET_TRACKING[[#This Row],[Variance]]/BUDGET_TRACKING[[#This Row],[PlannedSpend]])*100 -> -3.5714286 | I9: Labour | J9: Marco Rossi
A10: BGT-009 | B10: PRJ-002 | C10: =_xlfn.XLOOKUP(BUDGET_TRACKING[[#This Row],[ProjectID]],PROJECTS!A:A,PROJECTS!B:B,"Not Found") -> SOX Remediation Program | D10: 45383 | E10: 32000 | F10: 35500 | G10: =BUDGET_TRACKING[[#This Row],[ActualSpend]]-BUDGET_TRACKING[[#This Row],[PlannedSpend]] -> 3500 | H10: =(BUDGET_TRACKING[[#This Row],[Variance]]/BUDGET_TRACKING[[#This Row],[PlannedSpend]])*100 -> 10.9375 | I10: External | J10: Marco Rossi
A11: BGT-010 | B11: PRJ-002 | C11: =_xlfn.XLOOKUP(BUDGET_TRACKING[[#This Row],[ProjectID]],PROJECTS!A:A,PROJECTS!B:B,"Not Found") -> SOX Remediation Program | D11: 45413 | E11: 35000 | F11: 38000 | G11: =BUDGET_TRACKING[[#This Row],[ActualSpend]]-BUDGET_TRACKING[[#This Row],[PlannedSpend]] -> 3000 | H11: =(BUDGET_TRACKING[[#This Row],[Variance]]/BUDGET_TRACKING[[#This Row],[PlannedSpend]])*100 -> 8.5714286 | I11: External | J11: Marco Rossi
A12: BGT-011 | B12: PRJ-003 | C12: =_xlfn.XLOOKUP(BUDGET_TRACKING[[#This Row],[ProjectID]],PROJECTS!A:A,PROJECTS!B:B,"Not Found") -> Cloud Infrastructure Migration | D12: 45352 | E12: 80000 | F12: 78000 | G12: =BUDGET_TRACKING[[#This Row],[ActualSpend]]-BUDGET_TRACKING[[#This Row],[PlannedSpend]] -> -2000 | H12: =(BUDGET_TRACKING[[#This Row],[Variance]]/BUDGET_TRACKING[[#This Row],[PlannedSpend]])*100 -> -2.5 | I12: Labour | J12: David Chen
A13: BGT-012 | B13: PRJ-003 | C13: =_xlfn.XLOOKUP(BUDGET_TRACKING[[#This Row],[ProjectID]],PROJECTS!A:A,PROJECTS!B:B,"Not Found") -> Cloud Infrastructure Migration | D13: 45383 | E13: 120000 | F13: 125000 | G13: =BUDGET_TRACKING[[#This Row],[ActualSpend]]-BUDGET_TRACKING[[#This Row],[PlannedSpend]] -> 5000 | H13: =(BUDGET_TRACKING[[#This Row],[Variance]]/BUDGET_TRACKING[[#This Row],[PlannedSpend]])*100 -> 4.1666667 | I13: Technology | J13: David Chen
... A31: BGT-030 | B31: PRJ-022 | C31: =_xlfn.XLOOKUP(BUDGET_TRACKING[[#This Row],[ProjectID]],PROJECTS!A:A,PROJECTS!B:B,"Not Found") -> Payroll System Migration | D31: 45413 | E31: 35000 | F31: 34000 | G31: =BUDGET_TRACKING[[#This Row],[ActualSpend]]-BUDGET_TRACKING[[#This Row],[PlannedSpend]] -> -1000 | H31: =(BUDGET_TRACKING[[#This Row],[Variance]]/BUDGET_TRACKING[[#This Row],[PlannedSpend]])*100 -> -2.8571429 | I31: Labour | J31: Sarah Johnson
